<Stats BUILD_NAME="Noita-Build-Jan 25 2025-15:55:41" >
  <stats biomes_visited_with_wands="8" damage_taken="28.9538" dead="1" death_count="0" death_pos.x="-1369.05" death_pos.y="12276.9" enemies_killed="136" gold="743" gold_all="4893" gold_infinite="0" healed="3.8" heart_containers="0" hp="100" items="21" kicks="11" killed_by="Hohtava hyypiö | holy" killed_by_extra="" places_visited="8" playtime="2159.9" playtime_str="0:35:59" projectiles_shot="3076" streaks="0" teleports="0" wands_edited="11" world_seed="2019086331" >
  </stats>
  <biome_baseline biomes_visited_with_wands="7" damage_taken="20.1189" dead="0" death_count="0" death_pos.x="0" death_pos.y="0" enemies_killed="122" gold="143" gold_all="4293" gold_infinite="0" healed="3.8" heart_containers="0" hp="100" items="21" kicks="11" killed_by="" killed_by_extra="" places_visited="7" playtime="2018.43" playtime_str="0:33:38" projectiles_shot="2933" streaks="0" teleports="0" wands_edited="11" world_seed="2019086331" >
  </biome_baseline>
  <item_map>
  </item_map>
  <biomes_visited>
    <E key="$biome_coalmine" value="1" >
    </E>
    <E key="$biome_crypt" value="1" >
    </E>
    <E key="$biome_excavationsite" value="1" >
    </E>
    <E key="$biome_holymountain" value="1" >
    </E>
    <E key="$biome_rainforest" value="1" >
    </E>
    <E key="$biome_snowcastle" value="1" >
    </E>
    <E key="$biome_snowcave" value="1" >
    </E>
    <E key="$biome_vault" value="1" >
    </E>
  </biomes_visited>
</Stats>
