<Stats BUILD_NAME="Noita-Build-Jan 25 2025-15:55:41" >
  <stats biomes_visited_with_wands="3" damage_taken="11.464" dead="1" death_count="0" death_pos.x="-17.719" death_pos.y="1835.94" enemies_killed="24" gold="81" gold_all="81" gold_infinite="0" healed="0" heart_containers="0" hp="100" items="9" kicks="0" killed_by="Kranuhiisi | projectile" killed_by_extra="" places_visited="3" playtime="246.95" playtime_str="0:04:06" projectiles_shot="54" streaks="0" teleports="0" wands_edited="4" world_seed="483364837" >
  </stats>
  <biome_baseline biomes_visited_with_wands="2" damage_taken="4.484" dead="0" death_count="0" death_pos.x="0" death_pos.y="0" enemies_killed="23" gold="71" gold_all="71" gold_infinite="0" healed="0" heart_containers="0" hp="100" items="9" kicks="0" killed_by="" killed_by_extra="" places_visited="2" playtime="235.183" playtime_str="0:03:55" projectiles_shot="50" streaks="0" teleports="0" wands_edited="4" world_seed="483364837" >
  </biome_baseline>
  <item_map>
  </item_map>
  <biomes_visited>
    <E key="$biome_excavationsite" value="1" >
    </E>
    <E key="$biome_holymountain" value="1" >
    </E>
    <E key="$biome_snowcave" value="1" >
    </E>
  </biomes_visited>
</Stats>
